aiogram_cmds/__init__.py
aiogram_cmds/apply.py
aiogram_cmds/auto_setup.py
aiogram_cmds/builder.py
aiogram_cmds/builders_configured.py
aiogram_cmds/customize.py
aiogram_cmds/dynamic.py
aiogram_cmds/manager.py
aiogram_cmds/policy.py
aiogram_cmds/registry.py
aiogram_cmds/setters.py
aiogram_cmds/settings.py
aiogram_cmds/translator.py
aiogram_cmds/version.py
aiogram_cmds-0.1.1.dist-info/METADATA
aiogram_cmds-0.1.1.dist-info/WHEEL
aiogram_cmds-0.1.1.dist-info/licenses/LICENSE
aiogram_cmds-0.1.1.dist-info/RECORD
